ChatbotCreator/__init__.py
ChatbotCreator/cc.py
ChatbotCreator/dbot.py
ChatbotCreator/run.py
chatbot_creator-0.0.7.dist-info/LICENSE
chatbot_creator-0.0.7.dist-info/METADATA
chatbot_creator-0.0.7.dist-info/WHEEL
chatbot_creator-0.0.7.dist-info/top_level.txt
chatbot_creator-0.0.7.dist-info/RECORD
