Metadata-Version: 2.1
Name: chatbot-creator
Version: 0.0.7
Summary: Python package for creating chatbots.(including DiscordBot).
Home-page: https://github.com/My-refer/chatbot-creator
Author: Pranava Mohan
License: MIT
Platform: UNKNOWN
Classifier: Programming Language :: Python :: 3
Classifier: License :: OSI Approved :: MIT License
Classifier: Operating System :: OS Independent
Requires-Python: >=3.5
Requires-Dist: pandas
Requires-Dist: keras
Requires-Dist: sklearn
Requires-Dist: numpy
Requires-Dist: nltk
Requires-Dist: spacy
Requires-Dist: tensorflow
Requires-Dist: discord.py
Requires-Dist: google
Requires-Dist: bs4
